workflow/CacheableBase.py
workflow/PrepID.py
workflow/Task.py
workflow/Workflow.py
workflow/__init__.py
cmsworkflow-0.0.3.dist-info/LICENSE
cmsworkflow-0.0.3.dist-info/METADATA
cmsworkflow-0.0.3.dist-info/WHEEL
cmsworkflow-0.0.3.dist-info/top_level.txt
cmsworkflow-0.0.3.dist-info/RECORD
